Workbook

Sheet Portfolio  Holdings
B2: MF + ETF PORTFOLIO XIRR | D2: =C293 -> 0.19157735 | F2: NIFTY Return in the same period: | G2: =(F7/F6)^(1/F8) - 1 -> 0.1713798
B3: DATES | C3: AMOUNT | D3: Cum Sum
B4: 44126 | C4: -100 | D4: =IFERROR(__xludf.DUMMYFUNCTION("-(SUM($C$4:C4))"),100) -> 100 | E4: =B4 -> 44126 | F4: =E4 -> 44126
B5: 44126 | C5: -499 | D5: =IFERROR(__xludf.DUMMYFUNCTION("-(SUM($C$4:C5))"),599) -> 599 | E5: =B5 -> 44126 | F5: =TODAY()-1 -> 45861
B6: 44126 | C6: -499 | D6: =IFERROR(__xludf.DUMMYFUNCTION("-(SUM($C$4:C6))"),1098) -> 1098 | E6: =B6 -> 44126 | F6: =IFERROR(__xludf.DUMMYFUNCTION("INDEX(GOOGLEFINANCE(""NIFTY_50"", ""price"", F4), 2, 2)"),11896.45) -> 11896.45
B7: 44152 | C7: 101 | D7: =IFERROR(__xludf.DUMMYFUNCTION("-(SUM($C$4:C7))"),997) -> 997 | E7: =B7 -> 44152 | F7: =IFERROR(__xludf.DUMMYFUNCTION("INDEX(GOOGLEFINANCE(""NIFTY_50"", ""price"", F5), 2, 2)"),25219.9) -> 25219.9
B8: 44162 | C8: 495 | D8: =IFERROR(__xludf.DUMMYFUNCTION("-(SUM($C$4:C8))"),502) -> 502 | E8: =B8 -> 44162 | F8: =(F5-F4)/365.25 -> 4.7501711
B9: 44169 | C9: -499 | D9: =IFERROR(__xludf.DUMMYFUNCTION("-(SUM($C$4:C9))"),1001) -> 1001 | E9: =B9 -> 44169
B10: 44180 | C10: -499 | D10: =IFERROR(__xludf.DUMMYFUNCTION("-(SUM($C$4:C10))"),1500) -> 1500 | E10: =B10 -> 44180
B11: 44181 | C11: -499 | D11: =IFERROR(__xludf.DUMMYFUNCTION("-(SUM($C$4:C11))"),1999) -> 1999 | E11: =B11 -> 44181
B12: 44208 | C12: -999 | D12: =IFERROR(__xludf.DUMMYFUNCTION("-(SUM($C$4:C12))"),2998) -> 2998 | E12: =B12 -> 44208 | G12: Mutual Fund
B13: 44211 | C13: -499 | D13: =IFERROR(__xludf.DUMMYFUNCTION("-(SUM($C$4:C13))"),3497) -> 3497 | E13: =B13 -> 44211
B14: 44242 | C14: -499 | D14: =IFERROR(__xludf.DUMMYFUNCTION("-(SUM($C$4:C14))"),3996) -> 3996 | E14: =B14 -> 44242 | G14: Invested Value | H14: Profit | I14: Today
B15: 44242 | C15: -995 | D15: =IFERROR(__xludf.DUMMYFUNCTION("-(SUM($C$4:C15))"),4991) -> 4991 | E15: =B15 -> 44242 | G15: ='MF holdings and transactions'!A291 -> 98528 | H15: ='MF holdings and transactions'!B291 -> 36209 | I15: ='MF holdings and transactions'!C291 -> 60968.396
B16: 44242 | C16: 995 | D16: =IFERROR(__xludf.DUMMYFUNCTION("-(SUM($C$4:C16))"),3996) -> 3996 | E16: =B16 -> 44242
B17: 44242 | C17: -499 | D17: =IFERROR(__xludf.DUMMYFUNCTION("-(SUM($C$4:C17))"),4495) -> 4495 | E17: =B17 -> 44242 | G17: ETF
B18: 44270 | C18: -499 | D18: =IFERROR(__xludf.DUMMYFUNCTION("-(SUM($C$4:C18))"),4994) -> 4994 | E18: =B18 -> 44270
B19: 44270 | C19: -499 | D19: =IFERROR(__xludf.DUMMYFUNCTION("-(SUM($C$4:C19))"),5493) -> 5493 | E19: =B19 -> 44270 | G19: Invested Value | H19: Profit | I19: Today
B20: 44301 | C20: -499 | D20: =IFERROR(__xludf.DUMMYFUNCTION("-(SUM($C$4:C20))"),5992) -> 5992 | E20: =B20 -> 44301 | G20: ='Stocks Transaction'!I50 -> 25362.63 | H20: ='Stocks Transaction'!J50 -> 9296 | I20: ='Stocks Transaction'!K50 -> 23447.97
B21: 44301 | C21: -499 | D21: =IFERROR(__xludf.DUMMYFUNCTION("-(SUM($C$4:C21))"),6491) -> 6491 | E21: =B21 -> 44301 | J21: Profit + Today
B22: 44333 | C22: -499 | D22: =IFERROR(__xludf.DUMMYFUNCTION("-(SUM($C$4:C22))"),6990) -> 6990 | E22: =B22 -> 44333 | F22: TOTAL | G22: =G15+G20 -> 123890.63 | H22: =H15+H20 -> 45505 | I22: =I15+I20 -> 84416.366 | J22: =H22+I22 -> 129921.37
B23: 44333 | C23: -499 | D23: =IFERROR(__xludf.DUMMYFUNCTION("-(SUM($C$4:C23))"),7489) -> 7489 | E23: =B23 -> 44333 | I23: ABS RETURN | J23: =G22/J22 -> 0.95358165
B24: 44362 | C24: -499 | D24: =IFERROR(__xludf.DUMMYFUNCTION("-(SUM($C$4:C24))"),7988) -> 7988 | E24: =B24 -> 44362
B25: 44362 | C25: -499 | D25: =IFERROR(__xludf.DUMMYFUNCTION("-(SUM($C$4:C25))"),8487) -> 8487 | E25: =B25 -> 44362
B26: 44376 | C26: -3830 | D26: =IFERROR(__xludf.DUMMYFUNCTION("-(SUM($C$4:C26))"),12317) -> 12317 | E26: =B26 -> 44376
B27: 44376 | C27: 3830 | D27: =IFERROR(__xludf.DUMMYFUNCTION("-(SUM($C$4:C27))"),8487) -> 8487 | E27: =B27 -> 44376
B28: 44392 | C28: -499 | D28: =IFERROR(__xludf.DUMMYFUNCTION("-(SUM($C$4:C28))"),8986) -> 8986 | E28: =B28 -> 44392
B29: 44393 | C29: 1009 | D29: =IFERROR(__xludf.DUMMYFUNCTION("-(SUM($C$4:C29))"),7977) -> 7977 | E29: =B29 -> 44393
B30: 44393 | C30: -1009 | D30: =IFERROR(__xludf.DUMMYFUNCTION("-(SUM($C$4:C30))"),8986) -> 8986 | E30: =B30 -> 44393
B31: 44393 | C31: -499 | D31: =IFERROR(__xludf.DUMMYFUNCTION("-(SUM($C$4:C31))"),9485) -> 9485 | E31: =B31 -> 44393
B32: 44393 | C32: -499 | D32: =IFERROR(__xludf.DUMMYFUNCTION("-(SUM($C$4:C32))"),9984) -> 9984 | E32: =B32 -> 44393
B33: 44393 | C33: -499 | D33: =IFERROR(__xludf.DUMMYFUNCTION("-(SUM($C$4:C33))"),10483) -> 10483 | E33: =B33 -> 44393
B34: 44420 | C34: -199 | D34: =IFERROR(__xludf.DUMMYFUNCTION("-(SUM($C$4:C34))"),10682) -> 10682 | E34: =B34 -> 44420
B35: 44424 | C35: -499 | D35: =IFERROR(__xludf.DUMMYFUNCTION("-(SUM($C$4:C35))"),11181) -> 11181 | E35: =B35 -> 44424
B36: 44424 | C36: -499 | D36: =IFERROR(__xludf.DUMMYFUNCTION("-(SUM($C$4:C36))"),11680) -> 11680 | E36: =B36 -> 44424
B37: 44424 | C37: -499 | D37: =IFERROR(__xludf.DUMMYFUNCTION("-(SUM($C$4:C37))"),12179) -> 12179 | E37: =B37 -> 44424
B38: 44454 | C38: -199 | D38: =IFERROR(__xludf.DUMMYFUNCTION("-(SUM($C$4:C38))"),12378) -> 12378 | E38: =B38 -> 44454
B39: 44454 | C39: -499 | D39: =IFERROR(__xludf.DUMMYFUNCTION("-(SUM($C$4:C39))"),12877) -> 12877 | E39: =B39 -> 44454
B40: 44454 | C40: -499 | D40: =IFERROR(__xludf.DUMMYFUNCTION("-(SUM($C$4:C40))"),13376) -> 13376 | E40: =B40 -> 44454
B41: 44454 | C41: -499 | D41: =IFERROR(__xludf.DUMMYFUNCTION("-(SUM($C$4:C41))"),13875) -> 13875 | E41: =B41 -> 44454
B42: 44487 | C42: -499 | D42: =IFERROR(__xludf.DUMMYFUNCTION("-(SUM($C$4:C42))"),14374) -> 14374 | E42: =B42 -> 44487
B43: 44487 | C43: -499 | D43: =IFERROR(__xludf.DUMMYFUNCTION("-(SUM($C$4:C43))"),14873) -> 14873 | E43: =B43 -> 44487
B44: 44487 | C44: -199 | D44: =IFERROR(__xludf.DUMMYFUNCTION("-(SUM($C$4:C44))"),15072) -> 15072 | E44: =B44 -> 44487
B45: 44487 | C45: -499 | D45: =IFERROR(__xludf.DUMMYFUNCTION("-(SUM($C$4:C45))"),15571) -> 15571 | E45: =B45 -> 44487
B46: 44515 | C46: -499 | D46: =IFERROR(__xludf.DUMMYFUNCTION("-(SUM($C$4:C46))"),16070) -> 16070 | E46: =B46 -> 44515
B47: 44515 | C47: -199 | D47: =IFERROR(__xludf.DUMMYFUNCTION("-(SUM($C$4:C47))"),16269) -> 16269 | E47: =B47 -> 44515
B48: 44515 | C48: -499 | D48: =IFERROR(__xludf.DUMMYFUNCTION("-(SUM($C$4:C48))"),16768) -> 16768 | E48: =B48 -> 44515 | G48: Guideline to update sheet
B49: 44515 | C49: -499 | D49: =IFERROR(__xludf.DUMMYFUNCTION("-(SUM($C$4:C49))"),17267) -> 17267 | E49: =B49 -> 44515 | G49: 1) download mutual fund transation report (1) and mutual fund portfolio summary (2)
B50: 44524 | C50: -7955 | D50: =IFERROR(__xludf.DUMMYFUNCTION("-(SUM($C$4:C50))"),25222) -> 25222 | E50: =B50 -> 44524 | G50: 2) copy the new entries from 1 and paste in transactions. add comments if the purchase is special or write the reason if redeemed or switched
B51: 44524 | C51: 1024 | D51: =IFERROR(__xludf.DUMMYFUNCTION("-(SUM($C$4:C51))"),24198) -> 24198 | E51: =B51 -> 44524 | G51: 3) fill units, invested value from 2 to portfolio
B52: 44524 | C52: 7955 | D52: =IFERROR(__xludf.DUMMYFUNCTION("-(SUM($C$4:C52))"),16243) -> 16243 | E52: =B52 -> 44524 | G52: 4) pick entries from transaction to put in respected MF CAS transaction history, then calculate xirr and put it in the holdings.
B53: 44526 | C53: -1023 | D53: =IFERROR(__xludf.DUMMYFUNCTION("-(SUM($C$4:C53))"),17266) -> 17266 | E53: =B53 -> 44526 | G53: 5) add date and amount to portfolio to calculate net xirr
B54: 44543 | C54: -499 | D54: =IFERROR(__xludf.DUMMYFUNCTION("-(SUM($C$4:C54))"),17765) -> 17765 | E54: =B54 -> 44543 | G54: 6) update xirr without switch and mf+etf xirr calculations
B55: 44545 | C55: -499 | D55: =IFERROR(__xludf.DUMMYFUNCTION("-(SUM($C$4:C55))"),18264) -> 18264 | E55: =B55 -> 44545 | G55: 7) update and check for others in other cells, total fresh value invested, total invested, current portfolio value, diversification, cumsum chart, etc
B56: 44545 | C56: -199 | D56: =IFERROR(__xludf.DUMMYFUNCTION("-(SUM($C$4:C56))"),18463) -> 18463 | E56: =B56 -> 44545
B57: 44545 | C57: -499 | D57: =IFERROR(__xludf.DUMMYFUNCTION("-(SUM($C$4:C57))"),18962) -> 18962 | E57: =B57 -> 44545
B58: 44578 | C58: -499 | D58: =IFERROR(__xludf.DUMMYFUNCTION("-(SUM($C$4:C58))"),19461) -> 19461 | E58: =B58 -> 44578
B59: 44578 | C59: -499 | D59: =IFERROR(__xludf.DUMMYFUNCTION("-(SUM($C$4:C59))"),19960) -> 19960 | E59: =B59 -> 44578
B60: 44578 | C60: -499 | D60: =IFERROR(__xludf.DUMMYFUNCTION("-(SUM($C$4:C60))"),20459) -> 20459 | E60: =B60 -> 44578
B61: 44578 | C61: -199 | D61: =IFERROR(__xludf.DUMMYFUNCTION("-(SUM($C$4:C61))"),20658) -> 20658 | E61: =B61 -> 44578
B62: 44607 | C62: -499 | D62: =IFERROR(__xludf.DUMMYFUNCTION("-(SUM($C$4:C62))"),21157) -> 21157 | E62: =B62 -> 44607
B63: 44607 | C63: -499 | D63: =IFERROR(__xludf.DUMMYFUNCTION("-(SUM($C$4:C63))"),21656) -> 21656 | E63: =B63 -> 44607
B64: 44607 | C64: -199 | D64: =IFERROR(__xludf.DUMMYFUNCTION("-(SUM($C$4:C64))"),21855) -> 21855 | E64: =B64 -> 44607
B65: 44607 | C65: -499 | D65: =IFERROR(__xludf.DUMMYFUNCTION("-(SUM($C$4:C65))"),22354) -> 22354 | E65: =B65 -> 44607
B66: 44635 | C66: -499 | D66: =IFERROR(__xludf.DUMMYFUNCTION("-(SUM($C$4:C66))"),22853) -> 22853 | E66: =B66 -> 44635
B67: 44635 | C67: -199 | D67: =IFERROR(__xludf.DUMMYFUNCTION("-(SUM($C$4:C67))"),23052) -> 23052 | E67: =B67 -> 44635
B68: 44635 | C68: -499 | D68: =IFERROR(__xludf.DUMMYFUNCTION("-(SUM($C$4:C68))"),23551) -> 23551 | E68: =B68 -> 44635
B69: 44635 | C69: -499 | D69: =IFERROR(__xludf.DUMMYFUNCTION("-(SUM($C$4:C69))"),24050) -> 24050 | E69: =B69 -> 44635
B70: 44669 | C70: -199 | D70: =IFERROR(__xludf.DUMMYFUNCTION("-(SUM($C$4:C70))"),24249) -> 24249 | E70: =B70 -> 44669
B71: 44669 | C71: -499 | D71: =IFERROR(__xludf.DUMMYFUNCTION("-(SUM($C$4:C71))"),24748) -> 24748 | E71: =B71 -> 44669
B72: 44669 | C72: -499 | D72: =IFERROR(__xludf.DUMMYFUNCTION("-(SUM($C$4:C72))"),25247) -> 25247 | E72: =B72 -> 44669
B73: 44697 | C73: -499 | D73: =IFERROR(__xludf.DUMMYFUNCTION("-(SUM($C$4:C73))"),25746) -> 25746 | E73: =B73 -> 44697
B74: 44697 | C74: -199 | D74: =IFERROR(__xludf.DUMMYFUNCTION("-(SUM($C$4:C74))"),25945) -> 25945 | E74: =B74 -> 44697
B75: 44697 | C75: -499 | D75: =IFERROR(__xludf.DUMMYFUNCTION("-(SUM($C$4:C75))"),26444) -> 26444 | E75: =B75 -> 44697
B76: 44727 | C76: -199 | D76: =IFERROR(__xludf.DUMMYFUNCTION("-(SUM($C$4:C76))"),26643) -> 26643 | E76: =B76 -> 44727
B77: 44727 | C77: -499 | D77: =IFERROR(__xludf.DUMMYFUNCTION("-(SUM($C$4:C77))"),27142) -> 27142 | E77: =B77 -> 44727
B78: 44727 | C78: -499 | D78: =IFERROR(__xludf.DUMMYFUNCTION("-(SUM($C$4:C78))"),27641) -> 27641 | E78: =B78 -> 44727
B79: 44741 | C79: -742 | D79: =IFERROR(__xludf.DUMMYFUNCTION("-(SUM($C$4:C79))"),28383) -> 28383 | E79: =B79 -> 44741
B80: 44741 | C80: -721.6 | D80: =IFERROR(__xludf.DUMMYFUNCTION("-(SUM($C$4:C80))"),29104.6) -> 29104.6 | E80: =B80 -> 44741
B81: 44750 | C81: -999 | D81: =IFERROR(__xludf.DUMMYFUNCTION("-(SUM($C$4:C81))"),30103.6) -> 30103.6 | E81: =B81 -> 44750
B82: 44750 | C82: -469.9 | D82: =IFERROR(__xludf.DUMMYFUNCTION("-(SUM($C$4:C82))"),30573.5) -> 30573.5 | E82: =B82 -> 44750
B83: 44760 | C83: -199 | D83: =IFERROR(__xludf.DUMMYFUNCTION("-(SUM($C$4:C83))"),30772.5) -> 30772.5 | E83: =B83 -> 44760
B84: 44760 | C84: -499 | D84: =IFERROR(__xludf.DUMMYFUNCTION("-(SUM($C$4:C84))"),31271.5) -> 31271.5 | E84: =B84 -> 44760
B85: 44760 | C85: -499 | D85: =IFERROR(__xludf.DUMMYFUNCTION("-(SUM($C$4:C85))"),31770.5) -> 31770.5 | E85: =B85 -> 44760
B86: 44760 | C86: -566.28 | D86: =IFERROR(__xludf.DUMMYFUNCTION("-(SUM($C$4:C86))"),32336.78) -> 32336.78 | E86: =B86 -> 44760
B87: 44789 | C87: -499 | D87: =IFERROR(__xludf.DUMMYFUNCTION("-(SUM($C$4:C87))"),32835.78) -> 32835.78 | E87: =B87 -> 44789
B88: 44789 | C88: -199 | D88: =IFERROR(__xludf.DUMMYFUNCTION("-(SUM($C$4:C88))"),33034.78) -> 33034.78 | E88: =B88 -> 44789
B89: 44790 | C89: -499 | D89: =IFERROR(__xludf.DUMMYFUNCTION("-(SUM($C$4:C89))"),33533.78) -> 33533.78 | E89: =B89 -> 44790
B90: 44792 | C90: -523.1 | D90: =IFERROR(__xludf.DUMMYFUNCTION("-(SUM($C$4:C90))"),34056.88) -> 34056.88 | E90: =B90 -> 44792
B91: 44816 | C91: -491.65 | D91: =IFERROR(__xludf.DUMMYFUNCTION("-(SUM($C$4:C91))"),34548.53) -> 34548.53 | E91: =B91 -> 44816
B92: 44819 | C92: -499 | D92: =IFERROR(__xludf.DUMMYFUNCTION("-(SUM($C$4:C92))"),35047.53) -> 35047.53 | E92: =B92 -> 44819
B93: 44819 | C93: -199 | D93: =IFERROR(__xludf.DUMMYFUNCTION("-(SUM($C$4:C93))"),35246.53) -> 35246.53 | E93: =B93 -> 44819
B94: 44819 | C94: -499 | D94: =IFERROR(__xludf.DUMMYFUNCTION("-(SUM($C$4:C94))"),35745.53) -> 35745.53 | E94: =B94 -> 44819
B95: 44844 | C95: -457.35 | D95: =IFERROR(__xludf.DUMMYFUNCTION("-(SUM($C$4:C95))"),36202.88) -> 36202.88 | E95: =B95 -> 44844
B96: 44851 | C96: -499 | D96: =IFERROR(__xludf.DUMMYFUNCTION("-(SUM($C$4:C96))"),36701.88) -> 36701.88 | E96: =B96 -> 44851
B97: 44851 | C97: -199 | D97: =IFERROR(__xludf.DUMMYFUNCTION("-(SUM($C$4:C97))"),36900.88) -> 36900.88 | E97: =B97 -> 44851
B98: 44851 | C98: -499 | D98: =IFERROR(__xludf.DUMMYFUNCTION("-(SUM($C$4:C98))"),37399.88) -> 37399.88 | E98: =B98 -> 44851
B99: 44880 | C99: -499 | D99: =IFERROR(__xludf.DUMMYFUNCTION("-(SUM($C$4:C99))"),37898.88) -> 37898.88 | E99: =B99 -> 44880
B100: 44880 | C100: -499 | D100: =IFERROR(__xludf.DUMMYFUNCTION("-(SUM($C$4:C100))"),38397.88) -> 38397.88 | E100: =B100 -> 44880
B101: 44880 | C101: -199 | D101: =IFERROR(__xludf.DUMMYFUNCTION("-(SUM($C$4:C101))"),38596.88) -> 38596.88 | E101: =B101 -> 44880
...

Sheet MF holdings and transactions
A3: Personal Details
A4: Name
A5: Mobile Number
A6: PAN
B9: DATE
A10: TRANSACTIONS TILL | B10: =TODAY() -> 45862
P11: XIRR (WITHOUT SWITCH)
A12: Scheme Name | B12: Transaction Type | C12: Units | D12: NAV | E12: Amount | F12: Date | G12: Amount in/out | H12: ="2000 SIP Going (" & IF(DAY(TODAY()) > 17, DATEDIF(DATE(2024, 1, 1), TODAY(), "M") + 1, DATEDIF(DATE(2024, 1, 1), TODAY(), "M")) & ")" -> 2000 SIP Going (19) | P12: DATES | Q12: AMOUNT
A14: UTI Nifty200 Momentum 30 Index Fund Direct Growth | B14: PURCHASE | C14: 23.18 | D14: 21.57 | E14: 499 | F14: 45853 | G14: =IFERROR(__xludf.DUMMYFUNCTION("IF(E14="""", """", IF(OR(B14=""PURCHASE"", B14=""SWITCH PURCHASE""), E14*-1, E14)) "),-499) -> -499 | P14: 45853 | Q14: -499
A15: Nippon India Nifty Midcap 150 Index Fund Direct Growth | B15: PURCHASE | C15: 19.73 | D15: 25.35 | E15: 499 | F15: 45853 | G15: =IFERROR(__xludf.DUMMYFUNCTION("IF(E15="""", """", IF(OR(B15=""PURCHASE"", B15=""SWITCH PURCHASE""), E15*-1, E15)) "),-499) -> -499 | P15: 45853 | Q15: -499
A16: HDFC Short Term Debt Fund Direct Plan Growth | B16: PURCHASE | C16: 15.02 | D16: 33.29 | E16: 499 | F16: 45853 | G16: =IFERROR(__xludf.DUMMYFUNCTION("IF(E16="""", """", IF(OR(B16=""PURCHASE"", B16=""SWITCH PURCHASE""), E16*-1, E16)) "),-499) -> -499 | P16: 45853 | Q16: -499
A17: UTI Nifty200 Momentum 30 Index Fund Direct Growth | B17: PURCHASE | C17: 23 | D17: 21.74 | E17: 499 | F17: 45824 | G17: =IFERROR(__xludf.DUMMYFUNCTION("IF(E17="""", """", IF(OR(B17=""PURCHASE"", B17=""SWITCH PURCHASE""), E17*-1, E17)) "),-499) -> -499 | P17: 45824 | Q17: -499
A18: Nippon India Nifty Midcap 150 Index Fund Direct Growth | B18: PURCHASE | C18: 20.08 | D18: 24.9 | E18: 499 | F18: 45824 | G18: =IFERROR(__xludf.DUMMYFUNCTION("IF(E18="""", """", IF(OR(B18=""PURCHASE"", B18=""SWITCH PURCHASE""), E18*-1, E18)) "),-499) -> -499 | P18: 45824 | Q18: -499
A19: HDFC Short Term Debt Fund Direct Plan Growth | B19: PURCHASE | C19: 15.11 | D19: 33.09 | E19: 499 | F19: 45824 | G19: =IFERROR(__xludf.DUMMYFUNCTION("IF(E19="""", """", IF(OR(B19=""PURCHASE"", B19=""SWITCH PURCHASE""), E19*-1, E19)) "),-499) -> -499 | P19: 45824 | Q19: -499
A20: HDFC Short Term Debt Fund Direct Plan Growth | B20: REDEEM | C20: 30.57 | D20: 33.18 | E20: 1014 | F20: 45817 | G20: =IFERROR(__xludf.DUMMYFUNCTION("IF(E20="""", """", IF(OR(B20=""PURCHASE"", B20=""SWITCH PURCHASE""), E20*-1, E20)) "),1014) -> 1014 | P20: 45817 | Q20: 1014
A21: HDFC Short Term Debt Fund Direct Plan Growth | B21: PURCHASE | C21: 15.21 | D21: 32.88 | E21: 499 | F21: 45792 | G21: =IFERROR(__xludf.DUMMYFUNCTION("IF(E21="""", """", IF(OR(B21=""PURCHASE"", B21=""SWITCH PURCHASE""), E21*-1, E21)) "),-499) -> -499 | P21: 45792 | Q21: -499
A22: UTI Nifty200 Momentum 30 Index Fund Direct Growth | B22: PURCHASE | C22: 23.59 | D22: 21.19 | E22: 499 | F22: 45792 | G22: =IFERROR(__xludf.DUMMYFUNCTION("IF(E22="""", """", IF(OR(B22=""PURCHASE"", B22=""SWITCH PURCHASE""), E22*-1, E22)) "),-499) -> -499 | P22: 45792 | Q22: -499
A23: Nippon India Nifty Midcap 150 Index Fund Direct Growth | B23: PURCHASE | C23: 20.87 | D23: 23.96 | E23: 499 | F23: 45792 | G23: =IFERROR(__xludf.DUMMYFUNCTION("IF(E23="""", """", IF(OR(B23=""PURCHASE"", B23=""SWITCH PURCHASE""), E23*-1, E23)) "),-499) -> -499 | P23: 45792 | Q23: -499
A24: HDFC Short Term Debt Fund Direct Plan Growth | B24: PURCHASE | C24: 15.36 | D24: 32.55 | E24: 499 | F24: 45762 | G24: =IFERROR(__xludf.DUMMYFUNCTION("IF(E24="""", """", IF(OR(B24=""PURCHASE"", B24=""SWITCH PURCHASE""), E24*-1, E24)) "),-499) -> -499 | P24: 45762 | Q24: -499
A25: Nippon India Nifty Midcap 150 Index Fund Direct Growth | B25: PURCHASE | C25: 22.61 | D25: 22.12 | E25: 499 | F25: 45762 | G25: =IFERROR(__xludf.DUMMYFUNCTION("IF(E25="""", """", IF(OR(B25=""PURCHASE"", B25=""SWITCH PURCHASE""), E25*-1, E25)) "),-499) -> -499 | P25: 45762 | Q25: -499
A26: UTI Nifty200 Momentum 30 Index Fund Direct Growth | B26: PURCHASE | C26: 26.19 | D26: 19.09 | E26: 499 | F26: 45762 | G26: =IFERROR(__xludf.DUMMYFUNCTION("IF(E26="""", """", IF(OR(B26=""PURCHASE"", B26=""SWITCH PURCHASE""), E26*-1, E26)) "),-499) -> -499 | P26: 45762 | Q26: -499
A27: HDFC Short Term Debt Fund Direct Plan Growth | B27: PURCHASE | C27: 15.62 | D27: 32.01 | E27: 499 | F27: 45733 | G27: =IFERROR(__xludf.DUMMYFUNCTION("IF(E27="""", """", IF(OR(B27=""PURCHASE"", B27=""SWITCH PURCHASE""), E27*-1, E27)) "),-499) -> -499 | P27: 45733 | Q27: -499
A28: UTI Nifty200 Momentum 30 Index Fund Direct Growth | B28: PURCHASE | C28: 26.92 | D28: 18.57 | E28: 499 | F28: 45733 | G28: =IFERROR(__xludf.DUMMYFUNCTION("IF(E28="""", """", IF(OR(B28=""PURCHASE"", B28=""SWITCH PURCHASE""), E28*-1, E28)) "),-499) -> -499 | P28: 45733 | Q28: -499
A29: Nippon India Nifty Midcap 150 Index Fund Direct Growth | B29: PURCHASE | C29: 24.02 | D29: 20.81 | E29: 499 | F29: 45733 | G29: =IFERROR(__xludf.DUMMYFUNCTION("IF(E29="""", """", IF(OR(B29=""PURCHASE"", B29=""SWITCH PURCHASE""), E29*-1, E29)) "),-499) -> -499 | P29: 45733 | Q29: -499
A30: Nippon India Nifty Midcap 150 Index Fund Direct Growth | B30: PURCHASE | C30: 24.02 | D30: 20.81 | E30: 499 | F30: 45733 | G30: =IFERROR(__xludf.DUMMYFUNCTION("IF(E30="""", """", IF(OR(B30=""PURCHASE"", B30=""SWITCH PURCHASE""), E30*-1, E30)) "),-499) -> -499 | P30: 45733 | Q30: -499
A31: UTI Nifty200 Momentum 30 Index Fund Direct Growth | B31: PURCHASE | C31: 25.61 | D31: 19.52 | E31: 499 | F31: 45705 | G31: =IFERROR(__xludf.DUMMYFUNCTION("IF(E31="""", """", IF(OR(B31=""PURCHASE"", B31=""SWITCH PURCHASE""), E31*-1, E31)) "),-499) -> -499 | P31: 45705 | Q31: -499
A32: Nippon India Nifty Midcap 150 Index Fund Direct Growth | B32: PURCHASE | C32: 23.53 | D32: 21.25 | E32: 499 | F32: 45705 | G32: =IFERROR(__xludf.DUMMYFUNCTION("IF(E32="""", """", IF(OR(B32=""PURCHASE"", B32=""SWITCH PURCHASE""), E32*-1, E32)) "),-499) -> -499 | P32: 45705 | Q32: -499
A33: HDFC Short Term Debt Fund Direct Plan Growth | B33: PURCHASE | C33: 15.69 | D33: 31.87 | E33: 499 | F33: 45705 | G33: =IFERROR(__xludf.DUMMYFUNCTION("IF(E33="""", """", IF(OR(B33=""PURCHASE"", B33=""SWITCH PURCHASE""), E33*-1, E33)) "),-499) -> -499 | P33: 45705 | Q33: -499
A34: Nippon India Nifty Midcap 150 Index Fund Direct Growth | B34: PURCHASE | C34: 23.53 | D34: 21.25 | E34: 499 | F34: 45705 | G34: =IFERROR(__xludf.DUMMYFUNCTION("IF(E34="""", """", IF(OR(B34=""PURCHASE"", B34=""SWITCH PURCHASE""), E34*-1, E34)) "),-499) -> -499 | P34: 45705 | Q34: -499
A35: Nippon India Nifty Midcap 150 Index Fund Direct Growth | B35: PURCHASE | C35: 21.48 | D35: 23.28 | E35: 499 | F35: 45674 | G35: =IFERROR(__xludf.DUMMYFUNCTION("IF(E35="""", """", IF(OR(B35=""PURCHASE"", B35=""SWITCH PURCHASE""), E35*-1, E35)) "),-499) -> -499 | P35: 45674 | Q35: -499
A36: UTI Nifty200 Momentum 30 Index Fund Direct Growth | B36: PURCHASE | C36: 23.59 | D36: 21.19 | E36: 499 | F36: 45672 | G36: =IFERROR(__xludf.DUMMYFUNCTION("IF(E36="""", """", IF(OR(B36=""PURCHASE"", B36=""SWITCH PURCHASE""), E36*-1, E36)) "),-499) -> -499 | P36: 45672 | Q36: -499
A37: Nippon India Nifty Midcap 150 Index Fund Direct Growth | B37: PURCHASE | C37: 21.73 | D37: 23 | E37: 499 | F37: 45672 | G37: =IFERROR(__xludf.DUMMYFUNCTION("IF(E37="""", """", IF(OR(B37=""PURCHASE"", B37=""SWITCH PURCHASE""), E37*-1, E37)) "),-499) -> -499 | P37: 45672 | Q37: -499
A38: HDFC Short Term Debt Fund Direct Plan Growth | B38: PURCHASE | C38: 15.82 | D38: 31.6 | E38: 499 | F38: 45672 | G38: =IFERROR(__xludf.DUMMYFUNCTION("IF(E38="""", """", IF(OR(B38=""PURCHASE"", B38=""SWITCH PURCHASE""), E38*-1, E38)) "),-499) -> -499 | P38: 45672 | Q38: -499
A39: HDFC Short Term Debt Fund Direct Plan Growth | B39: PURCHASE | C39: 15.88 | D39: 31.49 | E39: 499 | F39: 45642 | G39: =IFERROR(__xludf.DUMMYFUNCTION("IF(E39="""", """", IF(OR(B39=""PURCHASE"", B39=""SWITCH PURCHASE""), E39*-1, E39)) "),-499) -> -499 | P39: 45642 | Q39: -499
A40: UTI Nifty200 Momentum 30 Index Fund Direct Growth | B40: PURCHASE | C40: 20.49 | D40: 24.4 | E40: 499 | F40: 45642 | G40: =IFERROR(__xludf.DUMMYFUNCTION("IF(E40="""", """", IF(OR(B40=""PURCHASE"", B40=""SWITCH PURCHASE""), E40*-1, E40)) "),-499) -> -499 | P40: 45642 | Q40: -499
A41: MOTILAL OSWAL NASDAQ 100 FUND OF FUND - DIRECT GROWTH | B41: PURCHASE | C41: 11.33 | D41: 44.13 | E41: 499 | F41: 45642 | G41: =IFERROR(__xludf.DUMMYFUNCTION("IF(E41="""", """", IF(OR(B41=""PURCHASE"", B41=""SWITCH PURCHASE""), E41*-1, E41)) "),-499) -> -499 | P41: 45642 | Q41: -499
A42: Nippon India Nifty Midcap 150 Index Fund Direct Growth | B42: PURCHASE | C42: 19.81 | D42: 25.24 | E42: 499 | F42: 45642 | G42: =IFERROR(__xludf.DUMMYFUNCTION("IF(E42="""", """", IF(OR(B42=""PURCHASE"", B42=""SWITCH PURCHASE""), E42*-1, E42)) "),-499) -> -499 | P42: 45642 | Q42: -499
A43: UTI Nifty200 Momentum 30 Index Fund Direct Growth | B43: PURCHASE | C43: 22.05 | D43: 22.67 | E43: 499 | F43: 45614 | G43: =IFERROR(__xludf.DUMMYFUNCTION("IF(E43="""", """", IF(OR(B43=""PURCHASE"", B43=""SWITCH PURCHASE""), E43*-1, E43)) "),-499) -> -499 | P43: 45614 | Q43: -499
A44: MOTILAL OSWAL NASDAQ 100 FUND OF FUND - DIRECT GROWTH | B44: PURCHASE | C44: 13.88 | D44: 36.04 | E44: 499 | F44: 45614 | G44: =IFERROR(__xludf.DUMMYFUNCTION("IF(E44="""", """", IF(OR(B44=""PURCHASE"", B44=""SWITCH PURCHASE""), E44*-1, E44)) "),-499) -> -499 | P44: 45614 | Q44: -499
A45: Nippon India Nifty Midcap 150 Index Fund Direct Growth | B45: PURCHASE | C45: 21.61 | D45: 23.14 | E45: 499 | F45: 45614 | G45: =IFERROR(__xludf.DUMMYFUNCTION("IF(E45="""", """", IF(OR(B45=""PURCHASE"", B45=""SWITCH PURCHASE""), E45*-1, E45)) "),-499) -> -499 | P45: 45614 | Q45: -499
A46: HDFC Short Term Debt Fund Direct Plan Growth | B46: PURCHASE | C46: 15.98 | D46: 31.29 | E46: 499 | F46: 45614 | G46: =IFERROR(__xludf.DUMMYFUNCTION("IF(E46="""", """", IF(OR(B46=""PURCHASE"", B46=""SWITCH PURCHASE""), E46*-1, E46)) "),-499) -> -499 | P46: 45614 | Q46: -499
A47: Nippon India Nifty Midcap 150 Index Fund Direct Growth | B47: PURCHASE | C47: 83.11 | D47: 24.06 | E47: 1999 | F47: 45596 | G47: =IFERROR(__xludf.DUMMYFUNCTION("IF(E47="""", """", IF(OR(B47=""PURCHASE"", B47=""SWITCH PURCHASE""), E47*-1, E47)) "),-1999) -> -1999 | H47: Total 4593 taken out here | P47: 45596 | Q47: -1999
A48: UTI Nifty200 Momentum 30 Index Fund Direct Growth | B48: PURCHASE | C48: 117.68 | D48: 23.79 | E48: 2799 | F48: 45596 | G48: =IFERROR(__xludf.DUMMYFUNCTION("IF(E48="""", """", IF(OR(B48=""PURCHASE"", B48=""SWITCH PURCHASE""), E48*-1, E48)) "),-2799) -> -2799 | P48: 45596 | Q48: -2799
A49: HDFC Short Term Debt Fund Direct Plan Growth | B49: REDEEM | C49: 299.91 | D49: 31.16 | E49: 9346 | F49: 45593 | G49: =IFERROR(__xludf.DUMMYFUNCTION("IF(E49="""", """", IF(OR(B49=""PURCHASE"", B49=""SWITCH PURCHASE""), E49*-1, E49)) "),9346) -> 9346 | P49: 45593 | Q49: 9346
A50: UTI Nifty200 Momentum 30 Index Fund Direct Growth | B50: PURCHASE | C50: 19.42 | D50: 25.74 | E50: 499 | F50: 45581 | G50: =IFERROR(__xludf.DUMMYFUNCTION("IF(E50="""", """", IF(OR(B50=""PURCHASE"", B50=""SWITCH PURCHASE""), E50*-1, E50)) "),-499) -> -499 | P50: 45581 | Q50: -499
A51: MOTILAL OSWAL NASDAQ 100 FUND OF FUND - DIRECT GROWTH | B51: PURCHASE | C51: 14.2 | D51: 35.21 | E51: 499 | F51: 45581 | G51: =IFERROR(__xludf.DUMMYFUNCTION("IF(E51="""", """", IF(OR(B51=""PURCHASE"", B51=""SWITCH PURCHASE""), E51*-1, E51)) "),-499) -> -499 | P51: 45581 | Q51: -499
A52: Nippon India Nifty Midcap 150 Index Fund Direct Growth | B52: PURCHASE | C52: 19.64 | D52: 25.46 | E52: 499 | F52: 45581 | G52: =IFERROR(__xludf.DUMMYFUNCTION("IF(E52="""", """", IF(OR(B52=""PURCHASE"", B52=""SWITCH PURCHASE""), E52*-1, E52)) "),-499) -> -499 | P52: 45581 | Q52: -499
A53: HDFC Short Term Debt Fund Direct Plan Growth | B53: PURCHASE | C53: 16.06 | D53: 31.14 | E53: 499 | F53: 45581 | G53: =IFERROR(__xludf.DUMMYFUNCTION("IF(E53="""", """", IF(OR(B53=""PURCHASE"", B53=""SWITCH PURCHASE""), E53*-1, E53)) "),-499) -> -499 | P53: 45581 | Q53: -499
A54: HDFC Short Term Debt Fund Direct Plan Growth | B54: PURCHASE | C54: 16.18 | D54: 30.89 | E54: 499 | F54: 45551 | G54: =IFERROR(__xludf.DUMMYFUNCTION("IF(E54="""", """", IF(OR(B54=""PURCHASE"", B54=""SWITCH PURCHASE""), E54*-1, E54)) "),-499) -> -499 | P54: 45551 | Q54: -499
A55: UTI Nifty200 Momentum 30 Index Fund Direct Growth | B55: PURCHASE | C55: 19.84 | D55: 25.2 | E55: 499 | F55: 45551 | G55: =IFERROR(__xludf.DUMMYFUNCTION("IF(E55="""", """", IF(OR(B55=""PURCHASE"", B55=""SWITCH PURCHASE""), E55*-1, E55)) "),-499) -> -499 | P55: 45551 | Q55: -499
A56: Nippon India Nifty Midcap 150 Index Fund Direct Growth | B56: PURCHASE | C56: 19.46 | D56: 25.69 | E56: 499 | F56: 45551 | G56: =IFERROR(__xludf.DUMMYFUNCTION("IF(E56="""", """", IF(OR(B56=""PURCHASE"", B56=""SWITCH PURCHASE""), E56*-1, E56)) "),-499) -> -499 | P56: 45551 | Q56: -499
A57: MOTILAL OSWAL NASDAQ 100 FUND OF FUND - DIRECT GROWTH | B57: PURCHASE | C57: 14.76 | D57: 33.88 | E57: 499 | F57: 45551 | G57: =IFERROR(__xludf.DUMMYFUNCTION("IF(E57="""", """", IF(OR(B57=""PURCHASE"", B57=""SWITCH PURCHASE""), E57*-1, E57)) "),-499) -> -499 | P57: 45551 | Q57: -499
A58: UTI Nifty200 Momentum 30 Index Fund Direct Growth | B58: PURCHASE | C58: 289.67 | D58: 25.2 | E58: 7299 | F58: 45527 | G58: =IFERROR(__xludf.DUMMYFUNCTION("IF(E58="""", """", IF(OR(B58=""PURCHASE"", B58=""SWITCH PURCHASE""), E58*-1, E58)) "),-7299) -> -7299 | H58: Total 35894(total redeemed - repurchased) - 14820(invested in MOM100) = 21074 taken out here | P58: 45527 | Q58: -7299
A59: Nippon India Nifty Midcap 150 Index Fund Direct Growth | B59: PURCHASE | C59: 292.23 | D59: 24.98 | E59: 7299 | F59: 45527 | G59: =IFERROR(__xludf.DUMMYFUNCTION("IF(E59="""", """", IF(OR(B59=""PURCHASE"", B59=""SWITCH PURCHASE""), E59*-1, E59)) "),-7299) -> -7299 | P59: 45527 | Q59: -7299
A60: UTI Nifty200 Momentum 30 Index Fund Direct Growth | B60: PURCHASE | C60: 20.21 | D60: 24.73 | E60: 499 | F60: 45520 | G60: =IFERROR(__xludf.DUMMYFUNCTION("IF(E60="""", """", IF(OR(B60=""PURCHASE"", B60=""SWITCH PURCHASE""), E60*-1, E60)) "),-499) -> -499 | P60: 45520 | Q60: -499
A61: MOTILAL OSWAL NASDAQ 100 FUND OF FUND - DIRECT GROWTH | B61: PURCHASE | C61: 14.71 | D61: 34 | E61: 499 | F61: 45520 | G61: =IFERROR(__xludf.DUMMYFUNCTION("IF(E61="""", """", IF(OR(B61=""PURCHASE"", B61=""SWITCH PURCHASE""), E61*-1, E61)) "),-499) -> -499 | P61: 45520 | Q61: -499
A62: Nippon India Nifty Midcap 150 Index Fund Direct Growth | B62: PURCHASE | C62: 20.35 | D62: 24.57 | E62: 499 | F62: 45520 | G62: =IFERROR(__xludf.DUMMYFUNCTION("IF(E62="""", """", IF(OR(B62=""PURCHASE"", B62=""SWITCH PURCHASE""), E62*-1, E62)) "),-499) -> -499 | P62: 45520 | Q62: -499
A63: HDFC Short Term Debt Fund Direct Plan Growth | B63: PURCHASE | C63: 16.32 | D63: 30.64 | E63: 499 | F63: 45520 | G63: =IFERROR(__xludf.DUMMYFUNCTION("IF(E63="""", """", IF(OR(B63=""PURCHASE"", B63=""SWITCH PURCHASE""), E63*-1, E63)) "),-499) -> -499 | P63: 45520 | Q63: -499
A64: HDFC Short Term Debt Fund Direct Plan Growth | B64: REDEEM | C64: 652.89 | D64: 30.63 | E64: 20000 | F64: 45518 | G64: =IFERROR(__xludf.DUMMYFUNCTION("IF(E64="""", """", IF(OR(B64=""PURCHASE"", B64=""SWITCH PURCHASE""), E64*-1, E64)) "),20000) -> 20000 | P64: 45518 | Q64: 20000
A65: Nippon India Nifty Midcap 150 Index Fund Direct Growth | B65: PURCHASE | C65: 411.33 | D65: 24.31 | E65: 9999 | F65: 45498 | G65: =IFERROR(__xludf.DUMMYFUNCTION("IF(E65="""", """", IF(OR(B65=""PURCHASE"", B65=""SWITCH PURCHASE""), E65*-1, E65)) "),-9999) -> -9999 | P65: 45498 | Q65: -9999
A66: UTI Nifty200 Momentum 30 Index Fund Direct Growth | B66: PURCHASE | C66: 412.32 | D66: 24.25 | E66: 9999 | F66: 45498 | G66: =IFERROR(__xludf.DUMMYFUNCTION("IF(E66="""", """", IF(OR(B66=""PURCHASE"", B66=""SWITCH PURCHASE""), E66*-1, E66)) "),-9999) -> -9999 | P66: 45498 | Q66: -9999
A67: HDFC Short Term Debt Fund Direct Plan Growth | B67: PURCHASE | C67: 747.59 | D67: 30.43 | E67: 22748 | F67: 45495 | G67: =IFERROR(__xludf.DUMMYFUNCTION("IF(E67="""", """", IF(OR(B67=""PURCHASE"", B67=""SWITCH PURCHASE""), E67*-1, E67)) "),-22748) -> -22748 | P67: 45495 | Q67: -22748
A68: Axis Midcap Direct Plan Growth | B68: REDEEM | C68: 62.06 | D68: 126.35 | E68: 7784 | F68: 45491 | G68: =IFERROR(__xludf.DUMMYFUNCTION("IF(E68="""", """", IF(OR(B68=""PURCHASE"", B68=""SWITCH PURCHASE""), E68*-1, E68)) "),7784) -> 7784 | P68: 45491 | Q68: 7784
A69: Axis Small Cap Fund Direct Growth | B69: REDEEM | C69: 23.72 | D69: 116.7 | E69: 2742 | F69: 45491 | G69: =IFERROR(__xludf.DUMMYFUNCTION("IF(E69="""", """", IF(OR(B69=""PURCHASE"", B69=""SWITCH PURCHASE""), E69*-1, E69)) "),2742) -> 2742 | P69: 45491 | Q69: 2742
A70: Aditya Birla Sun Life PSU Equity Fund Direct Growth | B70: REDEEM | C70: 2.51 | D70: 39.2 | E70: 98 | F70: 45491 | G70: =IFERROR(__xludf.DUMMYFUNCTION("IF(E70="""", """", IF(OR(B70=""PURCHASE"", B70=""SWITCH PURCHASE""), E70*-1, E70)) "),98) -> 98 | P70: 45491 | Q70: 98
A71: HDFC Short Term Debt Fund Direct Plan Growth | B71: PURCHASE | C71: 16.45 | D71: 30.39 | E71: 499 | F71: 45489 | G71: =IFERROR(__xludf.DUMMYFUNCTION("IF(E71="""", """", IF(OR(B71=""PURCHASE"", B71=""SWITCH PURCHASE""), E71*-1, E71)) "),-499) -> -499 | P71: 45489 | Q71: -499
A72: Axis Midcap Direct Plan Growth | B72: PURCHASE | C72: 3.92 | D72: 127.43 | E72: 499 | F72: 45489 | G72: =IFERROR(__xludf.DUMMYFUNCTION("IF(E72="""", """", IF(OR(B72=""PURCHASE"", B72=""SWITCH PURCHASE""), E72*-1, E72)) "),-499) -> -499 | P72: 45489 | Q72: -499
A73: Axis Small Cap Fund Direct Growth | B73: PURCHASE | C73: 4.26 | D73: 117.27 | E73: 499 | F73: 45489 | G73: =IFERROR(__xludf.DUMMYFUNCTION("IF(E73="""", """", IF(OR(B73=""PURCHASE"", B73=""SWITCH PURCHASE""), E73*-1, E73)) "),-499) -> -499 | P73: 45489 | Q73: -499
A74: MOTILAL OSWAL NASDAQ 100 FUND OF FUND - DIRECT GROWTH | B74: PURCHASE | C74: 13.96 | D74: 35.81 | E74: 499 | F74: 45489 | G74: =IFERROR(__xludf.DUMMYFUNCTION("IF(E74="""", """", IF(OR(B74=""PURCHASE"", B74=""SWITCH PURCHASE""), E74*-1, E74)) "),-499) -> -499 | P74: 45489 | Q74: -499
A75: Axis Short Term Direct Fund Growth | B75: REDEEM | C75: 1041.15 | D75: 30.9 | E75: 32168 | F75: 45488 | G75: =IFERROR(__xludf.DUMMYFUNCTION("IF(E75="""", """", IF(OR(B75=""PURCHASE"", B75=""SWITCH PURCHASE""), E75*-1, E75)) "),32168) -> 32168 | P75: 45488 | Q75: 32168
A76: ICICI Prudential Liquid Fund Direct Plan Growth | B76: REDEEM | C76: 52.61 | D76: 365.05 | E76: 19203 | F76: 45488 | G76: =IFERROR(__xludf.DUMMYFUNCTION("IF(E76="""", """", IF(OR(B76=""PURCHASE"", B76=""SWITCH PURCHASE""), E76*-1, E76)) "),19203) -> 19203 | P76: 45488 | Q76: 19203
A77: Tata Liquid Fund Direct Growth | B77: REDEEM | C77: 2.55 | D77: 3891.11 | E77: 9926 | F77: 45488 | G77: =IFERROR(__xludf.DUMMYFUNCTION("IF(E77="""", """", IF(OR(B77=""PURCHASE"", B77=""SWITCH PURCHASE""), E77*-1, E77)) "),9926) -> 9926 | P77: 45488 | Q77: 9926
A78: Parag Parikh Arbitrage Fund Direct Growth | B78: REDEEM | C78: 134.49 | D78: 10.55 | E78: 1419 | F78: 45488 | G78: =IFERROR(__xludf.DUMMYFUNCTION("IF(E78="""", """", IF(OR(B78=""PURCHASE"", B78=""SWITCH PURCHASE""), E78*-1, E78)) "),1419) -> 1419 | P78: 45488 | Q78: 1419
A79: UTI Nifty200 Momentum 30 Index Fund Direct Growth | B79: PURCHASE | C79: 19.96 | D79: 25.04 | E79: 499 | F79: 45489 | G79: =IFERROR(__xludf.DUMMYFUNCTION("IF(E79="""", """", IF(OR(B79=""PURCHASE"", B79=""SWITCH PURCHASE""), E79*-1, E79)) "),-499) -> -499 | P79: 45489 | Q79: -499
A80: Nippon India Nifty Midcap 150 Index Fund Direct Growth | B80: PURCHASE | C80: 20.21 | D80: 24.74 | E80: 499 | F80: 45489 | G80: =IFERROR(__xludf.DUMMYFUNCTION("IF(E80="""", """", IF(OR(B80=""PURCHASE"", B80=""SWITCH PURCHASE""), E80*-1, E80)) "),-499) -> -499 | P80: 45489 | Q80: -499
A81: Aditya Birla Sun Life PSU Equity Fund Direct Growth | B81: PURCHASE | C81: 2.51 | D81: 39.91 | E81: 100 | F81: 45489 | G81: =IFERROR(__xludf.DUMMYFUNCTION("IF(E81="""", """", IF(OR(B81=""PURCHASE"", B81=""SWITCH PURCHASE""), E81*-1, E81)) "),-100) -> -100 | P81: 45489 | Q81: -100
A82: Motilal Oswal Liquid Fund Direct Growth | B82: REDEEM | C82: 1551.31 | D82: 13.06 | E82: 20261 | F82: 45477 | G82: =IFERROR(__xludf.DUMMYFUNCTION("IF(E82="""", """", IF(OR(B82=""PURCHASE"", B82=""SWITCH PURCHASE""), E82*-1, E82)) "),20261) -> 20261 | P82: 45477 | Q82: 20261
A83: Axis Midcap Direct Plan Growth | B83: PURCHASE | C83: 4.03 | D83: 124 | E83: 499 | F83: 45462 | G83: =IFERROR(__xludf.DUMMYFUNCTION("IF(E83="""", """", IF(OR(B83=""PURCHASE"", B83=""SWITCH PURCHASE""), E83*-1, E83)) "),-499) -> -499 | P83: 45462 | Q83: -499
A84: HDFC Short Term Debt Fund Direct Plan Growth | B84: PURCHASE | C84: 16.56 | D84: 30.2 | E84: 499 | F84: 45462 | G84: =IFERROR(__xludf.DUMMYFUNCTION("IF(E84="""", """", IF(OR(B84=""PURCHASE"", B84=""SWITCH PURCHASE""), E84*-1, E84)) "),-499) -> -499 | P84: 45462 | Q84: -499
A85: Axis Small Cap Fund Direct Growth | B85: PURCHASE | C85: 4.43 | D85: 112.88 | E85: 499 | F85: 45462 | G85: =IFERROR(__xludf.DUMMYFUNCTION("IF(E85="""", """", IF(OR(B85=""PURCHASE"", B85=""SWITCH PURCHASE""), E85*-1, E85)) "),-499) -> -499 | P85: 45462 | Q85: -499
A86: MOTILAL OSWAL NASDAQ 100 FUND OF FUND - DIRECT GROWTH | B86: PURCHASE | C86: 14.44 | D86: 34.62 | E86: 499 | F86: 45462 | G86: =IFERROR(__xludf.DUMMYFUNCTION("IF(E86="""", """", IF(OR(B86=""PURCHASE"", B86=""SWITCH PURCHASE""), E86*-1, E86)) "),-499) -> -499 | P86: 45462 | Q86: -499
A87: Axis Midcap Direct Plan Growth | B87: PURCHASE | C87: 4.42 | D87: 113.17 | E87: 499 | F87: 45428 | G87: =IFERROR(__xludf.DUMMYFUNCTION("IF(E87="""", """", IF(OR(B87=""PURCHASE"", B87=""SWITCH PURCHASE""), E87*-1, E87)) "),-499) -> -499 | P87: 45428 | Q87: -499
A88: HDFC Short Term Debt Fund Direct Plan Growth | B88: PURCHASE | C88: 16.69 | D88: 29.96 | E88: 499 | F88: 45428 | G88: =IFERROR(__xludf.DUMMYFUNCTION("IF(E88="""", """", IF(OR(B88=""PURCHASE"", B88=""SWITCH PURCHASE""), E88*-1, E88)) "),-499) -> -499 | P88: 45428 | Q88: -499
A89: MOTILAL OSWAL NASDAQ 100 FUND OF FUND - DIRECT GROWTH | B89: PURCHASE | C89: 15.59 | D89: 32.07 | E89: 499 | F89: 45428 | G89: =IFERROR(__xludf.DUMMYFUNCTION("IF(E89="""", """", IF(OR(B89=""PURCHASE"", B89=""SWITCH PURCHASE""), E89*-1, E89)) "),-499) -> -499 | P89: 45428 | Q89: -499
A90: Axis Small Cap Fund Direct Growth | B90: PURCHASE | C90: 4.8 | D90: 104.16 | E90: 499 | F90: 45428 | G90: =IFERROR(__xludf.DUMMYFUNCTION("IF(E90="""", """", IF(OR(B90=""PURCHASE"", B90=""SWITCH PURCHASE""), E90*-1, E90)) "),-499) -> -499 | P90: 45428 | Q90: -499
A91: HDFC Short Term Debt Fund Direct Plan Growth | B91: PURCHASE | C91: 16.81 | D91: 29.74 | E91: 499 | F91: 45398 | G91: =IFERROR(__xludf.DUMMYFUNCTION("IF(E91="""", """", IF(OR(B91=""PURCHASE"", B91=""SWITCH PURCHASE""), E91*-1, E91)) "),-499) -> -499 | P91: 45398 | Q91: -499
A92: Axis Midcap Direct Plan Growth | B92: PURCHASE | C92: 4.72 | D92: 105.98 | E92: 499 | F92: 45398 | G92: =IFERROR(__xludf.DUMMYFUNCTION("IF(E92="""", """", IF(OR(B92=""PURCHASE"", B92=""SWITCH PURCHASE""), E92*-1, E92)) "),-499) -> -499 | P92: 45398 | Q92: -499
A93: Axis Small Cap Fund Direct Growth | B93: PURCHASE | C93: 4.97 | D93: 100.66 | E93: 499 | F93: 45398 | G93: =IFERROR(__xludf.DUMMYFUNCTION("IF(E93="""", """", IF(OR(B93=""PURCHASE"", B93=""SWITCH PURCHASE""), E93*-1, E93)) "),-499) -> -499 | P93: 45398 | Q93: -499
A94: MOTILAL OSWAL NASDAQ 100 FUND OF FUND - DIRECT GROWTH | B94: PURCHASE | C94: 15.83 | D94: 31.59 | E94: 499 | F94: 45397 | G94: =IFERROR(__xludf.DUMMYFUNCTION("IF(E94="""", """", IF(OR(B94=""PURCHASE"", B94=""SWITCH PURCHASE""), E94*-1, E94)) "),-499) -> -499 | P94: 45397 | Q94: -499
A95: Axis Midcap Direct Plan Growth | B95: PURCHASE | C95: 4.98 | D95: 100.32 | E95: 499 | F95: 45369 | G95: =IFERROR(__xludf.DUMMYFUNCTION("IF(E95="""", """", IF(OR(B95=""PURCHASE"", B95=""SWITCH PURCHASE""), E95*-1, E95)) "),-499) -> -499 | P95: 45369 | Q95: -499
A96: HDFC Short Term Debt Fund Direct Plan Growth | B96: PURCHASE | C96: 16.89 | D96: 29.6 | E96: 499 | F96: 45366 | G96: =IFERROR(__xludf.DUMMYFUNCTION("IF(E96="""", """", IF(OR(B96=""PURCHASE"", B96=""SWITCH PURCHASE""), E96*-1, E96)) "),-499) -> -499 | P96: 45366 | Q96: -499
A97: Axis Small Cap Fund Direct Growth | B97: PURCHASE | C97: 5.26 | D97: 95.08 | E97: 499 | F97: 45366 | G97: =IFERROR(__xludf.DUMMYFUNCTION("IF(E97="""", """", IF(OR(B97=""PURCHASE"", B97=""SWITCH PURCHASE""), E97*-1, E97)) "),-499) -> -499 | P97: 45366 | Q97: -499
A98: MOTILAL OSWAL NASDAQ 100 FUND OF FUND - DIRECT GROWTH | B98: PURCHASE | C98: 16.15 | D98: 30.96 | E98: 499 | F98: 45366 | G98: =IFERROR(__xludf.DUMMYFUNCTION("IF(E98="""", """", IF(OR(B98=""PURCHASE"", B98=""SWITCH PURCHASE""), E98*-1, E98)) "),-499) -> -499 | P98: 45366 | Q98: -499
A99: Axis Short Term Direct Fund Growth | B99: SWITCH PURCHASE | C99: 1041.15 | D99: 30.11 | E99: 31349 | F99: 45363 | G99: =IFERROR(__xludf.DUMMYFUNCTION("IF(E99="""", """", IF(OR(B99=""PURCHASE"", B99=""SWITCH PURCHASE""), E99*-1, E99)) "),-31349) -> -31349 | P99: 45337 | Q99: -499
A100: Motilal Oswal Liquid Fund Direct Growth | B100: SWITCH PURCHASE | C100: 1551.32 | D100: 12.79 | E100: 19834 | F100: 45358 | G100: =IFERROR(__xludf.DUMMYFUNCTION("IF(E100="""", """", IF(OR(B100=""PURCHASE"", B100=""SWITCH PURCHASE""), E100*-1, E100)) "),-19834) -> -19834 | P100: 45337 | Q100: -499
A101: Motilal Oswal Nasdaq 100 FOF Direct Growth | B101: SWITCH REDEEM | C101: 635.66 | D101: 31.2 | E101: 19835 | F101: 45358 | G101: =IFERROR(__xludf.DUMMYFUNCTION("IF(E101="""", """", IF(OR(B101=""PURCHASE"", B101=""SWITCH PURCHASE""), E101*-1, E101)) "),19835) -> 19835 | P101: 45337 | Q101: -499
A102: Axis Small Cap Fund Direct Growth | B102: SWITCH REDEEM | C102: 317.83 | D102: 98.64 | E102: 31350 | F102: 45358 | G102: =IFERROR(__xludf.DUMMYFUNCTION("IF(E102="""", """", IF(OR(B102=""PURCHASE"", B102=""SWITCH PURCHASE""), E102*-1, E102)) "),31350) -> 31350 | P102: 45337 | Q102: -499
A103: Axis Midcap Direct Plan Growth | B103: PURCHASE | C103: 4.97 | D103: 100.52 | E103: 499 | F103: 45337 | G103: =IFERROR(__xludf.DUMMYFUNCTION("IF(E103="""", """", IF(OR(B103=""PURCHASE"", B103=""SWITCH PURCHASE""), E103*-1, E103)) "),-499) -> -499 | P103: 45307 | Q103: -499
A104: MOTILAL OSWAL NASDAQ 100 FUND OF FUND - DIRECT GROWTH | B104: PURCHASE | C104: 16.3 | D104: 30.68 | E104: 499 | F104: 45337 | G104: =IFERROR(__xludf.DUMMYFUNCTION("IF(E104="""", """", IF(OR(B104=""PURCHASE"", B104=""SWITCH PURCHASE""), E104*-1, E104)) "),-499) -> -499 | P104: 45306 | Q104: -499
A105: HDFC Short Term Debt Fund Direct Plan Growth | B105: PURCHASE | C105: 17.01 | D105: 29.39 | E105: 499 | F105: 45337 | G105: =IFERROR(__xludf.DUMMYFUNCTION("IF(E105="""", """", IF(OR(B105=""PURCHASE"", B105=""SWITCH PURCHASE""), E105*-1, E105)) "),-499) -> -499 | P105: 45306 | Q105: -499
...

Sheet MF CAS
A1: ICICI Prudential Technology Fund - Direct - Growth
A3: Scheme Name | B3: Transaction Type | C3: Units | D3: NAV | E3: Amount | F3: Date | G3: Amount in/out
A4: ICICI Prudential Technology Fund - Direct - Growth | B4: REDEEM | C4: 1.1 | D4: 91.63 | E4: 101 | F4: 44152 | G4: 101
A5: ICICI Prudential Technology Fund - Direct - Growth | B5: PURCHASE | C5: 1.1 | D5: 90.46 | E5: 100 | F5: 44126 | G5: -100
A6: TOTAL | C6: 0
F7: XIRR | G7: 0.14991421
A8: Tata Liquid Fund Direct Growth
A10: Scheme Name | B10: Transaction Type | C10: Units | D10: NAV | E10: Amount | F10: Date | G10: Amount in/out
A11: Tata Liquid Fund Direct Growth | B11: REDEEM | C11: 2.55 | D11: 3891.11 | E11: 9926 | F11: 45488 | G11: 9926
A12: Tata Liquid Fund Direct Growth | B12: SWITCH PURCHASE | C12: 2.55 | D12: 3757.76 | E12: 9584 | F12: 45314 | G12: -9584
A13: TOTAL
F14: XIRR | G14: =XIRR(G11:G12,F11:F12) -> #NUM!
A15: ADITYA BIRLA SUN LIFE LIQUID FUND DIRECT PLAN - GROWTH
A17: Scheme Name | B17: Transaction Type | C17: Units | D17: NAV | E17: Amount | F17: Date | G17: Amount in/out
A18: ADITYA BIRLA SUN LIFE LIQUID FUND DIRECT PLAN - GROWTH | B18: SWITCH REDEEM | C18: 3.01 | D18: 334.82 | E18: 1009 | F18: 44393 | G18: 1009
A19: ADITYA BIRLA SUN LIFE LIQUID FUND DIRECT PLAN - GROWTH | B19: PURCHASE | C19: 3.01 | D19: 330.18 | E19: 995 | F19: 44242 | G19: -995
A20: TOTAL | C20: 0
F21: XIRR | G21: 0.034350881
A22: Parag Parikh Flexi Cap Fund Direct Growth
A24: Scheme Name | B24: Transaction Type | C24: Units | D24: NAV | E24: Amount | F24: Date | G24: Amount in/out
A25: Parag Parikh Flexi Cap Fund Direct Growth | B25: SWITCH REDEEM | C25: 19.19 | D25: 71.31 | E25: 1368 | F25: 45310 | G25: 1368
A26: Parag Parikh Flexi Cap Fund Direct Growth | B26: SWITCH PURCHASE | C26: 19.19 | D26: 53.35 | E26: 1023 | F26: 44526 | G26: -1023
A27: TOTAL | C27: 0
F28: XIRR | G28: 0.14487665
A29: ADITYA BIRLA SUN LIFE CORPORATE BOND FUND - GROWTH-DIRECT PLAN
A31: Scheme Name | B31: Transaction Type | C31: Units | D31: NAV | E31: Amount | F31: Date | G31: Amount in/out
A32: ADITYA BIRLA SUN LIFE CORPORATE BOND FUND - GROWTH-DIRECT PLAN | B32: SWITCH REDEEM | C32: 11.4 | D32: 89.9 | E32: 1024 | F32: 44524 | G32: 1024
A33: ADITYA BIRLA SUN LIFE CORPORATE BOND FUND - GROWTH-DIRECT PLAN | B33: SWITCH PURCHASE | C33: 11.4 | D33: 88.51 | E33: 1009 | F33: 44393 | G33: -1009
A34: ADITYA BIRLA SUN LIFE CORPORATE BOND FUND - GROWTH-DIRECT PLAN | B34: REDEEM | C34: 11.56 | D34: 86.06 | E34: 995 | F34: 44242 | G34: 995
A35: ADITYA BIRLA SUN LIFE CORPORATE BOND FUND - GROWTH-DIRECT PLAN | B35: PURCHASE | C35: 11.56 | D35: 86.48 | E35: 999 | F35: 44208 | G35: -999
A36: TOTAL | C36: 0
F37: XIRR | G37: 0.024111205
A38: ICICI Prudential Liquid Fund Direct Plan Growth
A40: Scheme Name | B40: Transaction Type | C40: Units | D40: NAV | E40: Amount | F40: Date | G40: Amount in/out
A41: ICICI Prudential Liquid Fund Direct Plan Growth | B41: REDEEM | C41: 52.61 | D41: 365.05 | E41: 19203 | F41: 45488 | G41: 19203
A42: ICICI Prudential Liquid Fund Direct Plan Growth | B42: SWITCH PURCHASE | C42: 52.61 | D42: 352.45 | E42: 18541 | F42: 45314 | G42: -18541
A43: TOTAL
F44: XIRR | G44: =XIRR(G41:G42,F41:F42) -> #NUM!
A45: Parag Parikh Arbitrage Fund Direct Growth
A47: Scheme Name | B47: Transaction Type | C47: Units | D47: NAV | E47: Amount | F47: Date | G47: Amount in/out
A48: Parag Parikh Arbitrage Fund Direct Growth | B48: REDEEM | C48: 134.49 | D48: 10.55 | E48: 1419 | F48: 45488 | G48: 1419
A49: Parag Parikh Arbitrage Fund Direct Growth | B49: SWITCH PURCHASE | C49: 134.49 | D49: 10.18 | E49: 1368 | F49: 45315 | G49: -1368
A50: TOTAL
F51: XIRR | G51: =XIRR(G48:G49,F48:F49) -> #NUM!
A52: HDFC Short Term Debt Fund Direct Plan Growth
A54: Scheme Name | B54: Transaction Type | C54: Units | D54: NAV | E54: Amount | F54: Date | G54: Amount in/out
A55: HDFC Short Term Debt Fund Direct Plan Growth | B55: PURCHASE | C55: 747.59 | D55: 30.43 | E55: 22748 | F55: 45495 | G55: -22748
A56: HDFC Short Term Debt Fund Direct Plan Growth | B56: PURCHASE | C56: 16.45 | D56: 30.39 | E56: 499 | F56: 45489 | G56: -499
A57: HDFC Short Term Debt Fund Direct Plan Growth | B57: PURCHASE | C57: 16.56 | D57: 30.2 | E57: 499 | F57: 45462 | G57: -499
A58: HDFC Short Term Debt Fund Direct Plan Growth | B58: PURCHASE | C58: 16.69 | D58: 29.96 | E58: 499 | F58: 45428 | G58: -499
A59: HDFC Short Term Debt Fund Direct Plan Growth | B59: PURCHASE | C59: 16.81 | D59: 29.74 | E59: 499 | F59: 45398 | G59: -499
A60: HDFC Short Term Debt Fund Direct Plan Growth | B60: PURCHASE | C60: 16.89 | D60: 29.6 | E60: 499 | F60: 45366 | G60: -499
A61: HDFC Short Term Debt Fund Direct Plan Growth | B61: PURCHASE | C61: 17.01 | D61: 29.39 | E61: 499 | F61: 45337 | G61: -499
A62: HDFC Short Term Debt Fund Direct Plan Growth | B62: PURCHASE | C62: 17.13 | D62: 29.19 | E62: 499 | F62: 45307 | G62: -499
A63: HDFC Short Term Debt Fund Direct Plan Growth | B63: PURCHASE | C63: 3.45 | D63: 28.99 | E63: 100 | F63: 45275 | G63: -100
A64: HDFC Short Term Debt Fund Direct Plan Growth | B64: PURCHASE | C64: 3.47 | D64: 28.8 | E64: 100 | F64: 45245 | G64: -100
A65: HDFC Short Term Debt Fund Direct Plan Growth | B65: PURCHASE | C65: 3.5 | D65: 28.58 | E65: 100 | F65: 45215 | G65: -100
A66: HDFC Short Term Debt Fund Direct Plan Growth | B66: PURCHASE | C66: 3.51 | D66: 28.52 | E66: 100 | F66: 45184 | G66: -100
... A83: HDFC Short Term Debt Fund Direct Plan Growth | B83: PURCHASE | C83: 15.69 | D83: 31.87 | E83: 499 | F83: 45705 | G83: -499
A84: HDFC Short Term Debt Fund Direct Plan Growth | B84: PURCHASE | C84: 15.36 | D84: 32.55 | E84: 499 | F84: 45762 | G84: =IFERROR(__xludf.DUMMYFUNCTION("IF(E84="""", """", IF(OR(B84=""PURCHASE"", B84=""SWITCH PURCHASE""), E84*-1, E84)) "),-499) -> -499
A85: HDFC Short Term Debt Fund Direct Plan Growth | B85: PURCHASE | C85: 15.11 | D85: 33.09 | E85: 499 | F85: 45824 | G85: =IFERROR(__xludf.DUMMYFUNCTION("IF(E85="""", """", IF(OR(B85=""PURCHASE"", B85=""SWITCH PURCHASE""), E85*-1, E85)) "),-499) -> -499
A86: HDFC Short Term Debt Fund Direct Plan Growth | B86: REDEEM | C86: 30.57 | D86: 33.18 | E86: 1014 | F86: 45817 | G86: =IFERROR(__xludf.DUMMYFUNCTION("IF(E86="""", """", IF(OR(B86=""PURCHASE"", B86=""SWITCH PURCHASE""), E86*-1, E86)) "),1014) -> 1014
A87: HDFC Short Term Debt Fund Direct Plan Growth | B87: PURCHASE | C87: 15.21 | D87: 32.88 | E87: 499 | F87: 45792 | G87: =IFERROR(__xludf.DUMMYFUNCTION("IF(E87="""", """", IF(OR(B87=""PURCHASE"", B87=""SWITCH PURCHASE""), E87*-1, E87)) "),-499) -> -499
A88: HDFC Short Term Debt Fund Direct Plan Growth | B88: PURCHASE | C88: 15.02 | D88: 33.29 | E88: 499 | F88: 45853 | G88: =IFERROR(__xludf.DUMMYFUNCTION("IF(E88="""", """", IF(OR(B88=""PURCHASE"", B88=""SWITCH PURCHASE""), E88*-1, E88)) "),-499) -> -499
A89: TOTAL | C89: ='MF holdings and transactions'!I303 -> 30.127 | D89: ='MF holdings and transactions'!G303 -> 33.35 | F89: =TODAY() -> 45862 | G89: ='MF holdings and transactions'!K303 -> 1004.7355
F90: XIRR | G90: =XIRR(G55:G89,F55:F89) -> -0.36254491
A91: Axis Midcap Fund - Direct - Growth
A93: Scheme Name | B93: Transaction Type | C93: Units | D93: NAV | E93: Amount | F93: Date | G93: Amount in/out
A94: Axis Midcap Direct Plan Growth | B94: REDEEM | C94: 62.06 | D94: 126.35 | E94: 7784 | F94: 45491 | G94: 7784
A95: Axis Midcap Direct Plan Growth | B95: PURCHASE | C95: 3.92 | D95: 127.43 | E95: 499 | F95: 45489 | G95: -499
A96: Axis Midcap Fund - Direct - Growth | B96: PURCHASE | C96: 4.03 | D96: 124 | E96: 499 | F96: 45462 | G96: -499
A97: Axis Midcap Fund - Direct - Growth | B97: PURCHASE | C97: 4.42 | D97: 113.17 | E97: 499 | F97: 45428 | G97: -499
A98: Axis Midcap Fund - Direct - Growth | B98: PURCHASE | C98: 4.72 | D98: 105.98 | E98: 499 | F98: 45398 | G98: -499
A99: Axis Midcap Fund - Direct - Growth | B99: PURCHASE | C99: 4.98 | D99: 100.32 | E99: 499 | F99: 45369 | G99: -499
A100: Axis Midcap Fund - Direct - Growth | B100: PURCHASE | C100: 4.97 | D100: 100.52 | E100: 499 | F100: 45337 | G100: -499
A101: Axis Midcap Fund - Direct - Growth | B101: PURCHASE | C101: 5.03 | D101: 99.38 | E101: 499 | F101: 45306 | G101: -499
A102: Axis Midcap Fund - Direct - Growth | B102: PURCHASE | C102: 5.14 | D102: 97.19 | E102: 499 | F102: 45275 | G102: -499
A103: Axis Midcap Fund - Direct - Growth | B103: PURCHASE | C103: 5.51 | D103: 90.8 | E103: 499 | F103: 45245 | G103: -499
A104: Axis Midcap Fund - Direct - Growth | B104: PURCHASE | C104: 2.21 | D104: 90.49 | E104: 199 | F104: 45215 | G104: -199
A105: Axis Midcap Fund - Direct - Growth | B105: PURCHASE | C105: 2.21 | D105: 90.41 | E105: 199 | F105: 45184 | G105: -199
... A125: Axis Midcap Fund - Direct - Growth | B125: PURCHASE | C125: 10.67 | D125: 46.84 | E125: 499 | F125: 44126 | G125: -499
A126: TOTAL
F127: XIRR | G127: =XIRR(G94:G125,F94:F125) -> #NUM!
A128: Tata Digital India Fund Direct Growth
A130: Scheme Name | B130: Transaction Type | C130: Units | D130: NAV | E130: Amount | F130: Date | G130: Amount in/out
A131: Tata Digital India Fund Direct Growth | B131: SWITCH REDEEM | C131: 194.61 | D131: 49.25 | E131: 9585 | F131: 45310 | G131: 9585
A132: Tata Digital India Fund Direct Growth | B132: PURCHASE | C132: 4.23 | D132: 47.26 | E132: 199 | F132: 45275 | G132: -199
A133: Tata Digital India Fund Direct Growth | B133: PURCHASE | C133: 4.67 | D133: 42.83 | E133: 199 | F133: 45245 | G133: -199
A134: Tata Digital India Fund Direct Growth | B134: PURCHASE | C134: 4.84 | D134: 41.3 | E134: 199 | F134: 45215 | G134: -199
A135: Tata Digital India Fund Direct Growth | B135: PURCHASE | C135: 4.69 | D135: 42.67 | E135: 199 | F135: 45184 | G135: -199
A136: Tata Digital India Fund Direct Growth | B136: PURCHASE | C136: 5.03 | D136: 39.76 | E136: 199 | F136: 45154 | G136: -199
A137: Tata Digital India Fund Direct Growth | B137: PURCHASE | C137: 5.04 | D137: 39.69 | E137: 199 | F137: 45124 | G137: -199
A138: Tata Digital India Fund Direct Growth | B138: PURCHASE | C138: 5.39 | D138: 37.08 | E138: 199 | F138: 45092 | G138: -199
A139: Tata Digital India Fund Direct Growth | B139: PURCHASE | C139: 5.63 | D139: 35.52 | E139: 199 | F139: 45061 | G139: -199
A140: Tata Digital India Fund Direct Growth | B140: PURCHASE | C140: 5.91 | D140: 33.84 | E140: 199 | F140: 45033 | G140: -199
A141: Tata Digital India Fund Direct Growth | B141: PURCHASE | C141: 5.69 | D141: 35.15 | E141: 199 | F141: 45000 | G141: -199
A142: Tata Digital India Fund Direct Growth | B142: PURCHASE | C142: 5.33 | D142: 37.55 | E142: 199 | F142: 44972 | G142: -199
... A164: Tata Digital India Fund Direct Growth | B164: PURCHASE | C164: 22.38 | D164: 22.34 | E164: 499 | F164: 44126 | G164: -499
A165: TOTAL | C165: -5.6843419e-14
F166: XIRR | G166: 0.21102948
...

Sheet Stocks Transaction
A1: Personal Details
A2: Name
A3: Unique Client Code
A5: =CONCATENATE("P&L Statement for stocks from 11-06-2020 TO ", TEXT(TODAY(), "DD-MM-YYYY")) -> P&L Statement for stocks from 11-06-2020 TO 24-07-2025
A8: Stocks
A10: Stock name | B10: ISIN | C10: Quantity | D10: Buy date | E10: Buy price | F10: Buy value | G10: Sell date | H10: Sell price | I10: Sell value | J10: UN/Realised P&L
A11: FEDERAL BANK LTD | B11: INE171A01029 | C11: 2 | D11: 44130 | E11: 56.3 | F11: 112.6 | G11: 44186 | H11: 65.2 | I11: 130.4 | J11: 17.8
A12: VODAFONE IDEA LIMITED | B12: INE669E01016 | C12: 6 | D12: 44130 | E12: 9.05 | F12: 54.3 | G12: 44186 | H12: 9.9 | I12: 59.4 | J12: 5.1
A13: ITC LTD | B13: INE154A01025 | C13: 2 | D13: 44130 | E13: 171.5 | F13: 343 | G13: 44186 | H13: 212.6 | I13: 425.2 | J13: 82.2
A14: TATA MOTORS LIMITED | B14: INE155A01022 | C14: 1 | D14: 44130 | E14: 138.4 | F14: 138.4 | G14: 44186 | H14: 176.75 | I14: 176.75 | J14: 38.35
A15: SPICEJET LTD. | B15: INE285B01017 | C15: 2 | D15: 44130 | E15: 52.65 | F15: 105.3 | G15: 44186 | H15: 97.05 | I15: 194.1 | J15: 88.8
A16: YES BANK LIMITED | B16: INE528G01035 | C16: 6 | D16: 44130 | E16: 13.95 | F16: 83.7 | G16: 44186 | H16: 18.7 | I16: 112.2 | J16: 28.5
A17: VISA STEEL LIMITED | B17: INE286H01012 | C17: 1 | D17: 44132 | E17: 6.15 | F17: 6.15 | G17: 44147 | H17: 5.5 | I17: 5.5 | J17: -0.65
A18: GTL INFRA.LTD | B18: INE221H01019 | C18: 1 | D18: 44134 | E18: 0.65 | F18: 0.65 | G18: 44147 | H18: 0.6 | I18: 0.6 | J18: -0.05
A19: PAZEL | B19: INE040N01029 | C19: 1 | D19: 44140 | E19: 0.25 | F19: 0.25 | G19: 44149 | H19: 0.2 | I19: 0.2 | J19: -0.05
A20: ZEE ENTERTAINMENT ENT LTD | B20: INE256A01028 | C20: 3 | D20: 44037 | E20: 141.12 | F20: 423.36 | G20: 45593 | H20: 119.7 | I20: 359.1 | J20: -64.26
A21: ZEE ENTERTAINMENT ENT LTD | B21: INE256A01028 | C21: 1 | D21: 45523 | E21: 135.4 | F21: 135.4 | G21: 45593 | H21: 119.7 | I21: 119.7 | J21: -15.7
A22: TOTAL | F22: =SUM(F11:F21) -> 1403.11 | I22: =SUM(I11:I21) -> 1583.15 | J22: =SUM(J11:J21) -> 180.04
I23: Abs Returns | J23: =J22/F22 -> 0.12831496
A25: ETF
A27: Stock name | B27: ISIN | C27: Quantity | D27: Buy date | E27: Buy price | F27: Buy value | G27: Sell date | H27: Sell price | I27: Sell value | J27: UN/Realised P&L
A28: MOTILAL OS NASDAQ100 ETF | B28: INF247L01AP3 | C28: 8 | D28: 44741 | E28: 90.2 | F28: 721.6 | G28: 45357 | H28: 145.25 | I28: 1162 | J28: 440.4
A29: MOTILAL OS NASDAQ100 ETF | B29: INF247L01AP3 | C29: 5 | D29: 44750 | E29: 93.98 | F29: 469.9 | G29: 45357 | H29: 145.25 | I29: 726.25 | J29: 256.35
A30: MOTILAL OS NASDAQ100 ETF | B30: INF247L01AP3 | C30: 6 | D30: 44760 | E30: 94.38 | F30: 566.28 | G30: 45357 | H30: 145.25 | I30: 871.5 | J30: 305.22
A31: MOTILAL OS NASDAQ100 ETF | B31: INF247L01AP3 | C31: 5 | D31: 44792 | E31: 104.62 | F31: 523.1 | G31: 45357 | H31: 145.25 | I31: 726.25 | J31: 203.15
A32: MOTILAL OS NASDAQ100 ETF | B32: INF247L01AP3 | C32: 5 | D32: 44816 | E32: 98.33 | F32: 491.65 | G32: 45357 | H32: 145.25 | I32: 726.25 | J32: 234.6
A33: MOTILAL OS NASDAQ100 ETF | B33: INF247L01AP3 | C33: 5 | D33: 44844 | E33: 91.47 | F33: 457.35 | G33: 45357 | H33: 145.25 | I33: 726.25 | J33: 268.9
A34: MOTILAL OS NASDAQ100 ETF | B34: INF247L01AP3 | C34: 5 | D34: 44882 | E34: 93.01 | F34: 465.05 | G34: 45357 | H34: 145.25 | I34: 726.25 | J34: 261.2
A35: MOTILAL OS NASDAQ100 ETF | B35: INF247L01AP3 | C35: 6 | D35: 44914 | E35: 92.82 | F35: 556.92 | G35: 45357 | H35: 145.25 | I35: 871.5 | J35: 314.58
A36: MOTILAL OS NASDAQ100 ETF | B36: INF247L01AP3 | C36: 10 | D36: 44960 | E36: 99.96 | F36: 999.6 | G36: 45357 | H36: 145.25 | I36: 1452.5 | J36: 452.9 | K36: =IFERROR(__xludf.DUMMYFUNCTION("(-SUM(F28:F44)+SUM(I28:I44))"),7381.33999999999) -> 7381.34 | L36: Returns till now
A37: MOTILAL OS NASDAQ100 ETF | B37: INF247L01AP3 | C37: 9 | D37: 44965 | E37: 102.01 | F37: 918.09 | G37: 45357 | H37: 145.25 | I37: 1307.25 | J37: 389.16 | K37: =IFERROR(__xludf.DUMMYFUNCTION("(-SUM(F28:F37)+SUM(I28:I37))/SUM(F28:F37)"),0.50675739196115) -> 0.50675739 | L37: in percentage
A38: MOTILAL OS NASDAQ100 ETF | B38: INF247L01AP4 | C38: 60 | D38: 45498 | E38: 159.17 | F38: 9550.2 | G38: =TODAY() -> 45862 | H38: =IFERROR(__xludf.DUMMYFUNCTION("GOOGLEFINANCE(""MON100"")"),200.41) -> 200.41 | I38: =C38*H38 -> 12024.6 | J38: =I38-F38 -> 2474.4
A39: MOTILAL OS NASDAQ100 ETF | B39: INF247L01AP3 | C39: 33 | D39: 45523 | E39: 159.69 | F39: 5269.77 | G39: =TODAY() -> 45862 | H39: =IFERROR(__xludf.DUMMYFUNCTION("GOOGLEFINANCE(""MON100"")"),200.41) -> 200.41 | I39: =C39*H39 -> 6613.53 | J39: =I39-F39 -> 1343.76
A40: MOTILAL OS NASDAQ100 ETF | B40: INF247L01AP3 | C40: 7 | D40: 45741 | E40: 186.06 | F40: 1302.42 | G40: =TODAY() -> 45862 | H40: =IFERROR(__xludf.DUMMYFUNCTION("GOOGLEFINANCE(""MON100"")"),200.41) -> 200.41 | I40: =C40*H40 -> 1402.87 | J40: =I40-F40 -> 100.45
A41: MOTILAL OS NASDAQ100 ETF | B41: INF247L01AP3 | C41: 3 | D41: 45764 | E41: 164.48 | F41: 493.44 | G41: =TODAY() -> 45862 | H41: =IFERROR(__xludf.DUMMYFUNCTION("GOOGLEFINANCE(""MON100"")"),200.41) -> 200.41 | I41: =C41*H41 -> 601.23 | J41: =I41-F41 -> 107.79
A42: MOTILAL OS NASDAQ100 ETF | B42: INF247L01AP3 | C42: 8 | D42: 45817 | E42: 181.78 | F42: 1454.24 | G42: =TODAY() -> 45862 | H42: =IFERROR(__xludf.DUMMYFUNCTION("GOOGLEFINANCE(""MON100"")"),200.41) -> 200.41 | I42: =C42*H42 -> 1603.28 | J42: =I42-F42 -> 149.04
A43: MOTILAL OS NASDAQ100 ETF | B43: INF247L01AP3 | C43: 3 | D43: 45825 | E43: 181.79 | F43: 545.37 | G43: =TODAY() -> 45862 | H43: =IFERROR(__xludf.DUMMYFUNCTION("GOOGLEFINANCE(""MON100"")"),200.41) -> 200.41 | I43: =C43*H43 -> 601.23 | J43: =I43-F43 -> 55.86
A44: MOTILAL OS NASDAQ100 ETF | B44: INF247L01AP3 | C44: 3 | D44: 45854 | E44: 192.55 | F44: 577.65 | G44: =TODAY() -> 45862 | H44: =IFERROR(__xludf.DUMMYFUNCTION("GOOGLEFINANCE(""MON100"")"),200.41) -> 200.41 | I44: =C44*H44 -> 601.23 | J44: =I44-F44 -> 23.58
A45: TOTAL (current) | F45: =SUM(F38:F44) -> 19193.09 | I45: =SUM(I38:I44) -> 23447.97 | J45: =I45-F45 -> 4254.88
I46: Abs Returns | J46: =J45/F45 -> 0.22168812
A48: MOTILAL OS NASDAQ100 ETF XIRR CALCULATION | E48: MOTILAL OS NAS100 NET XIRR CALCULATION
A49: Dates | B49: Amount in/out | E49: Dates | F49: Amount in/out | I49: Total Fresh Invested Value | J49: Amount Taken out (not just profit) | K49: Current Portfolio Value
A50: 44741 | B50: -721.6 | E50: 44376 | F50: -3830 | I50: =SUM(F28:F44) -> 25362.63 | J50: =SUM(I28:I37) -> 9296 | K50: =I45 -> 23447.97
A51: 44750 | B51: -469.9 | E51: 44393 | F51: -499
A52: 44760 | B52: -566.28 | E52: 44424 | F52: -499
A53: 44792 | B53: -523.1 | E53: 44454 | F53: -499
A54: 44816 | B54: -491.65 | E54: 44487 | F54: -499
A55: 44844 | B55: -457.35 | E55: 44515 | F55: -499
A56: 44882 | B56: -465.05 | E56: 44545 | F56: -499
A57: 44914 | B57: -556.92 | E57: 44578 | F57: -499
A58: 44960 | B58: -999.6 | E58: 44607 | F58: -499
A59: 44965 | B59: -918.09 | E59: 44635 | F59: -499
A60: 45357 | B60: 9296 | C60: ="PROFIT TILL " & SUM(B50:B60) -> PROFIT TILL 3126.46 | E60: 44741 | F60: -721.6
A61: 45498 | B61: -9550.2 | E61: 44750 | F61: -469.9
A62: 45523 | B62: -5269.77 | E62: 44760 | F62: -566.28
A63: 45741 | B63: 1302.42 | E63: 44792 | F63: -523.1
A64: 45764 | B64: 493.44 | E64: 44816 | F64: -491.65
A65: 45817 | B65: 1454.24 | E65: 44844 | F65: -457.35
A66: 45825 | B66: 545.37 | E66: 44882 | F66: -465.05
A67: 45854 | B67: 577.65 | E67: 44914 | F67: -556.92
A68: =TODAY() -> 45862 | B68: =SUM(I38:I44) -> 23447.97 | E68: 44942 | F68: -499
A69: XIRR | B69: =XIRR(B50:B68,A50:A68) -> 0.59892656 | E69: 44960 | F69: -999.6
E70: 44965 | F70: -918.09
E71: 44972 | F71: -499
E72: 45000 | F72: -499
E73: 45033 | F73: -499
E74: 45061 | F74: -499
E75: 45092 | F75: -499
E76: 45124 | F76: -499
E77: 45154 | F77: -499
E78: 45184 | F78: -499
E79: 45215 | F79: -499
E80: 45245 | F80: -499
E81: 45275 | F81: -499
... E98: 45854 | F98: 577.65
E99: =TODAY() -> 45862 | F99: =SUM(I38:I44) -> 23447.97
E100: =TODAY() -> 45862 | F100: ='MF holdings and transactions'!K302 -> 6075.8702
E102: XIRR | F102: =XIRR(F50:F100,E50:E100) -> 0.35713416
